BirdJumpExtreme/__init__.py
BirdJumpExtreme/terminal_game.py
BirdJumpExtreme-0.0.1.dist-info/LICENSE.txt
BirdJumpExtreme-0.0.1.dist-info/METADATA
BirdJumpExtreme-0.0.1.dist-info/WHEEL
BirdJumpExtreme-0.0.1.dist-info/top_level.txt
BirdJumpExtreme-0.0.1.dist-info/RECORD
