Metadata-Version: 2.1
Name: BirdJumpExtreme
Version: 0.0.1
Summary: A fun platform-jumping game for your terminal
Home-page: https://github.com/PhilippRados/BirdJumpExtreme
Author: Philipp Rados
Author-email: phil.rados@gmail.com
License: UNKNOWN
Platform: UNKNOWN
Classifier: Programming Language :: Python :: 3
Classifier: License :: OSI Approved :: MIT License
Classifier: Operating System :: OS Independent
Requires-Python: >=3.6
